pymailer/__about__.py
pymailer/__init__.py
pymailer/core/__init__.py
pymailer/core/email_service.py
pymailer/tests/__init__.py
pymailer/utils/__init__.py
pymailer/utils/message.py
py3mailer-1.0.6.dist-info/LICENSE
py3mailer-1.0.6.dist-info/METADATA
py3mailer-1.0.6.dist-info/WHEEL
py3mailer-1.0.6.dist-info/top_level.txt
py3mailer-1.0.6.dist-info/RECORD
