Metadata-Version: 2.1
Name: py3mailer
Version: 1.0.6
Summary: A simple and convinient way to send emails in python
Home-page: https://github.com/complexsum/pymailer
Author: Shubham Sharma
Author-email: shubhamjsharma10@gmail.com
License: Apache 2.0
Project-URL: Bug Reports, https://github.com/complexsum/pymailer/issues
Project-URL: Source, https://github.com/complexsum/pymailer
Keywords: email,python email,python smtp,python send emails,smtp
Platform: UNKNOWN
Classifier: Development Status :: 3 - Alpha
Classifier: Intended Audience :: Developers
Classifier: Topic :: Utilities
Classifier: License :: OSI Approved :: Apache Software License
Classifier: Programming Language :: Python :: 3
Classifier: Programming Language :: Python :: 3.6
Classifier: Programming Language :: Python :: 3.7
Classifier: Programming Language :: Python :: 3.8
Classifier: Programming Language :: Python :: 3.9
Classifier: Programming Language :: Python :: 3 :: Only
Classifier: Operating System :: OS Independent
Classifier: Typing :: Typed
Requires-Python: >=3.6, <4
